[
  {
    "listing": "/index.html",
    "items": [
      "/qmd/blog/quarto-reveal.html",
      "/qmd/dsblog.html",
      "/qmd/posts.html",
      "/qmd/projects.html",
      "/qmd/slides.html",
      "/qmd/slides-older.html"
    ]
  },
  {
    "listing": "/qmd/posts.html",
    "items": [
      "/qmd/ezpz/ezpz.html",
      "/qmd/slides.html",
      "/qmd/dsblog.html",
      "/qmd/features.html",
      "/qmd/blog/quarto-reveal.html",
      "/qmd/projects.html",
      "/qmd/slides-older.html"
    ]
  },
  {
    "listing": "/qmd/features.html",
    "items": [
      "/qmd/blog/quarto-reveal.html"
    ]
  }
]